{
  "id": "1776898839210_",
  "media_id": "1776898839210_",
  "platform": "unknown",
  "ts": 0,
  "transcript": "1\n00:00:00,879 --> 00:00:59,439\n[SPEAKER_00] As-salamu alaykum wa rahmatullahi wa barakatuhu. Bismillah ar-Rahman ar-Rahim. Mahmadoon wa salli ala rasoolin kareem. Amma ba'al. I think somebody took my book and... Okay, yeah. Alright, Bismillah ar-Rahman ar-Rahim. Mahmadoon wa salli ala rasoolin kareem. Amma ba'al. So, alhamdulillah, last time we finished entirely the 10th lesson. Nothing left here to do. So, inshallah, we can move on to lesson number 11. But before we do that, we did have some homework. It was optional, though, but if anybody did it, then they can, inshallah, present it.\n\n2\n00:01:00,000 --> 00:01:57,200\n[SPEAKER_00] The homework was to basically, if anybody has examples of these dama'ir, pronouns that we learned from the Qur'an. Min ladun hu. Yeah, good. Inshallah. From him. Min ladun hu means from him. Good. Yeah. Laha ma kasabat wa alayha maktasabat. Yeah. So, the ha, the dama'ir, the pronouns going back to the nafs. La yukallifu allahu nafsan illa wus'aha lahaa. Because remember we mentioned that nafs is one of those words which, even though there's no ta'am ar-buta, but they're female. It's a feminine word. Right? So, that's why we say lahaa. Right? Laha ma kasabat. So, that ha, dama'ir is for feminine words.\n\n3\n00:02:00,600 --> 00:02:59,900\n[SPEAKER_00] Good. Alayka tawakkalna. Alayka is when you take ala, when you put ala, and you connect it with the ka, it becomes alayka. So, this becomes a ya. And so, you say alayka. Right? So, upon you do we trust. Alayka tawakkalna. Understood? Understood? Yes? Yes. Tawakkalna. Okay. Good. Any other examples? Yeah. Wa lam yakun lahu kufuan ahad. And there is no, there is no match for Allah subhanahu wa ta'ala, for him. Right? Or a match or anyone who is superior or who is like Allah subhanahu wa ta'ala. Yeah. Subhanaka. Glory be to you. How much?\n\n4\n00:03:00,300 --> 00:03:59,919\n[SPEAKER_00] Allahu illaha illa huwal hayal kayyum. No, there's no, specifically the pronoun that we were looking for are not in there. But, yeah, good try though. Inshallah. Yeah. Good. Yeah. Good. Bi rabuwa tin asaba hawa. Wa matha allatheena yunfiquna amwaala. Wa matha allatheena yunfiquna amwaala humu butiqaa mardaatillahi wa tathbeetan min anfusihim. Ka matha li jannatin bi rabuwa tin asaba hawaabil. So waabil is basically a torrential rain. A very powerful rain. Storm, you could say. So, jannah is referring to a garden. Right? So Allah is giving the example of a person who spends in the way of Allah subhanahu wa ta'ala. For the sake of Allah. For seeking the pleasure of Allah subhanahu wa ta'ala. And so Allah is saying,\n\n5\n00:04:00,000 --> 00:04:59,800\n[SPEAKER_00] that it's like a garden that's a heavy rain. Asaba ha. It afflicts it. Meaning it basically pours onto it. Asaba ha. So the ha is going back to jannah, which is a feminine word. So that's why the female pronoun is used. Okay. Yeah. Good. Same ayah. Same thing. Yeah. Good. Good. Yeah. Ma aghna anhu ma luhu wa ma kasab. His wealth, ma luhu, his wealth, meaning Abu Lahab's wealth. Ma aghna anhu. It did not help him. It will not benefit him. Ma luhu wa ma kasab. Yeah. Good. Wa mra'atuhu and his wife. Imra'a means a woman and imra'atuhu means his woman, meaning his wife.\n\n6\n00:05:00,000 --> 00:05:56,519\n[SPEAKER_00] So wa mra'atuhu, his wife. Zawjiha. Good. Yeah. Qad sami'allahu qawla allati tujadiluka fi zawjiha. What is tujadiluka? Right? Arguing with you. Meaning it's a story of Khawla bin Sa'labah radiallahu anha and how the situation that happened between her and her husband and how she complained to Nabi sallallahu alayhi wa sallam. And so, tujadiluka. She was basically going back and forth with you fi zawjiha regarding her husband, her husband, zawjiha. Okay. Somebody. Ma'i. Good. Yeah. Fa'arsin ma'iya bani Israel. Ma'i. With me. So ma'a. You have ma'a. But then you add the ya. Means ma'i. With me.\n\n7\n00:06:00,000 --> 00:06:59,959\n[SPEAKER_00] Good. Inna ka. Let me know. Inna is something inshallah come in the second book. Inna is for extra emphasis. So, inna ka. It would be surely you or indeed you. Right? Inna ka. Let me know. Indeed or surely you are from the messengers. Wa ma'a daraaka. Yeah. There's many ayat. Yeah. Yeah. Wa ma'a daraaka ma'a hiya. For example, in Surah Qari'ah. So, and what will make you know? Good. So, ith qala rabbuka. And when your Lord said to the angels. Rabbuka. Your Lord. Good. Good. As in the durood. Right? Inna ka. Indeed you are praiseworthy and glorious. Good. Inna ka. Good. Allah is. Addressing Musa Alayhi Salaam.\n\n8\n00:07:00,000 --> 00:08:01,079\n[SPEAKER_00] Telling him that indeed you, inna ka, are in the blessed valley of Tua. Good. Waladina yu'minuna bima undila ilayka. And those who believe in that which was revealed to you. We already know ila. Right? Ila. Ila means to. Right? I went to. Blank. Right? They have to ila al-masjid, for example. Ila means to. So, ilayka. You just add the. When you add a kaf to it, it becomes ilayka. Just like ala becomes alayka. If you add a ka to ila, it becomes ilayka. Right? So, bima undila ilayka. Those who believe in that which was revealed to you. Meaning to Nabi Sallallahu Alaihi Wasallam. Good. Good. To him belongs that\n\n9\n00:08:01,079 --> 00:08:59,879\n[SPEAKER_00] which is in the heavens and the earth. Meaning Allah Subhanahu Wa Ta'ala. Good. Inna shani aka huwal abtar. Shani means a person who hates. A hater. Right? So, indeed, your hater. Shani aka. Your hater. Allah is addressing Nabi Sallallahu Alaihi Wasallam. Surely, your hater is the one who is abtar. Who is cut off. Right? Why? Because if you look at the tafsir of the ayah. One of the kuffar of Mecca. He was trying to make fun of Nabi Sallallahu Alaihi Wasallam. That his children would all. Male children would all pass away. And so, he called him abtar. That he's like a person who's. Like a lizard whose tail is cut off, for example. Because a person who did not have children. Would be considered as if they had no legacy. Nobody to take on their name after they passed away. So, Allah Subhanahu Wa Ta'ala told him. That rather, you're not the one who's cut off. Allah is giving you kawthar. Great abundance. Your hater. The one who said that statement.\n\n10\n00:09:00,019 --> 00:10:00,460\n[SPEAKER_00] Your hater is the one who is cut off. So, Allah Subhanahu Wa Ta'ala. Responded on behalf of his beloved Nabi Sallallahu Alaihi Wasallam. And assured him. That he is not cut off. Rather, his hater is the one who is cut off. And history has proved that statement to be true. As those people are basically in the dustbins of history. Nobody even knows. Really cares about their name. Except maybe you'll read it in a tafsir book. But nobody cares about them. And their very own children. Instead of upholding their legacy. They ended up following the legacy of Rasulullah Sallallahu Alaihi Wasallam. And so, Nabi Sallallahu Alaihi Wasallam has the greatest legacy of any human being. To step foot on the face of the earth. Despite him not having any children. So, Your hater. Surah Yusuf. Good, yeah. Yeah. She is the wife.\n\n11\n00:10:00,820 --> 00:11:00,179\n[SPEAKER_00] Basically, now the women are talking smack about the wife of the Aziz Zulaikha. Because she basically was trying to commit a certain act with Yusuf Sallallahu Alaihi Wasallam. And so, they started spreading rumors and talking about her. That, oh, she is trying to. She is trying to seduce her. Her, basically, her slave. Her slave. Her servant. Despite his, basically, resistance. Yeah, but over there, there's no pronoun that we mentioned. Because Nuhyi, the Yadir is from the actual verb itself. It's not for... Yeah, yeah. But you did have another\n\n12\n00:11:00,179 --> 00:12:01,139\n[SPEAKER_00] one there, which is أَحْصَيْنَاهُ فِي كِتَابِ فِي إِمَامِ مُبِينٍ Yeah. And we have, basically, encompassed everything in a clear book. فَصَلِّ لِرَبِّكَ Good. فَصَلِّ لِرَبِّكَ And pray for your Lord. For the sake of your Lord. Your Lord. رَبِّكَ Yeah, good. Yeah, one of those mentioned that already. Good. أَلَّمَهُ الْبَيَانِ The beginning of Surah Ar-Rahman. Allah is saying that He taught him al-bayan, speech. Very good, good example, yeah. قُلْ إِنَّ صَلَاتِي وَنُسُكِي وَمَحْيَايَ وَمَمَاتِي لِلَّهِ رَبِّ الْعَالَمِينَ Indeed, my salah, my\n\n13\n00:12:01,139 --> 00:13:00,639\n[SPEAKER_00] sacrifice, my life, مَحْيَايَ وَمَمَاتِي وَمَمَاتِي لِلَّهِ is for Allah subhanahu wa ta'ala, رَبِّ الْعَالَمِينَ the Lord of the universe. What a beautiful ayah, right? إِنَّ صَلَاتِي وَمَمَاتِي وَمَمَاتِي لِلَّهِ There is still the same thing. It's still the pronoun for me. And my life, وَمَمَاتِي وَمَمَاتِي لِلَّهِ is for Allah subhanahu wa ta'ala, Lord. The Lord of the universe. Sorry? Yeah, إِسْمُهُ أَحْمَلُ Yeah, didn't we mention that last class? Okay, لَا إِلَهَ إِلَّا أَنْتَ سُبْحَانَكَ Yeah, glory be to you. Good. Good. اللَّهُمَّ أَعِنِّي أَعِنِّي أَوَّ اللَّهِ help me أَعِنِّي عَلَى\n\n14\n00:13:00,639 --> 00:14:00,059\n[SPEAKER_00] ذِكْرِكَ to remember you. ذِكْر We know it means remembrance of Allah. ذِكْرِكَ Allah help me to remember you. وَشُكْرِكَ and to thank you. وَحُسْنِيَعِبَادَتِكَ and to worship you in a beautiful حُسْن حُسْن means beauty. وَحُسْنِيَعِبَادَتِكَ and to worship you in a beautiful manner. Very good. So there's multiple. Again, if we ponder and really focus on the Quran, you'll literally find it. So that's why we shouldn't think it's a waste of time. This is actually, inshallah, solidifying this. More and more we hear, more examples we hear, inshallah, it becomes solidified in our mind. The different pronouns. Any more examples? لَا تَأْخُذُهُ Yeah, good. لَا تَأْخُذُهُ Talking about Allah subhanahu wa ta'ala in Ayat al-Kursi. That neither drowsiness nor sleep overcomes Him. Allah subhanahu wa ta'ala. إِذْ وَالْفِكْسِيَةُ إِذَا\n\n15\n00:14:00,059 --> 00:15:00,340\n[SPEAKER_00] الْكَافِي فَقَوْنُوا رَبَّنَا أَتِنَا مِنَ الدُّنْكَ رَحْمَةٌ أَفِكْرُونَ Yeah, I think you said مِن لَدُّنْكَ already. I said it a second time. Oh, a second, yeah. But yeah, same concept. مِن لَدُّنْكَ وَجَعَلْنِي مِن وَرَثَةِ جَنَّةِ النَّعِيمِ Yeah, good. وَجَعَلْنِي مِن وَرَثَةِ جَنَّةِ النَّعِيمِ Ibrahim a.s. is making du'a to Allah subhanahu wa ta'ala and make me from the inheritors of the gardens of bliss. وَجَعَلْنِي مِن وَرَثَةِ جَنَّةِ النَّعِيمِ رَبِّ شْرَحْ لِي صَدْرِي My Lord, basically expand my chest for me. لِي وَيَسِّرْ لِي أَمْرِي وَيَسِّرْ لِي أَمْرِي And make... وَيَسِّرْ لِي أَمْرِي My matter easy for me. Right? وَحَدُ الْعُقْدَةَ مِّن لِيسَانِي And untie this knot in my tongue. From my tongue. لِيسَانِي لِيسَان means tongue. لِيسَانِي means my tongue. وَيَفْقَهُ قَوْلِي\n\n16\n00:15:00,340 --> 00:16:00,179\n[SPEAKER_00] So they may understand my statement, my speech. قَوْلِي Okay, I think it's enough examples, inshallah. But you see again, that we should really, really be pondering now. We know a lot, actually. If you really take a step back and try to implement all the rules that we've learned so far, and you start looking at the Qur'an, you can actually realize that you actually know a lot of different words. Right now, it's still a little bit early, but inshallah, soon, you'll get to the point where... The main thing is once you figure out how to basically figure out what are the root letters of a word. Right? Once you figure that out, then I'll teach you how to use an Arabic dictionary. Once you learn how to use an Arabic dictionary, basically, the sky is the limit. Because now you can look up any word in the Qur'an, and you can figure out, okay, what tense is it used in, what form is it used in, what\n\n17\n00:16:00,179 --> 00:17:00,379\n[SPEAKER_00] context is it used in, and through that, inshallah, you can go even further. Right now, you're a little bit limited. I don't want to take you further than you're able to right now. But even then, if you were to just apply... if you were to apply everything you know so far, you'd realize that you would actually know quite a bit, and you're actually able to grasp a lot. Alright, let's get started on lesson 11, inshallah. In the name of Allah, the Most Gracious, the Most Merciful. Who wants to read? This is my house. My house is in front of the Masjid. Imam? In front of the Masjid. In front of the Masjid. Good. So, why is it Al-Masjidi? There's a dharf behind it. Good, very good. Amama is a dharf, which means that it's mudhaf to the word after it, and it makes the word after it kasra. And a dharf indicates? Time and place. Yeah, place or time. In this case, it indicates\n\n18\n00:17:00,379 --> 00:17:58,819\n[SPEAKER_00] place. So, translate. This is my house. My house is in front of the Masjid. Good. Yeah, my house is in front of the Masjid. My house is beautiful. So humble, mashallah. Mashallah. Feehi hadeeqatun sagheeratun. In his? Oh, in it is... Let him figure it out. Sorry. What is hadeeqa? Hadeeqa, can anybody remind him what is hadeeqa? Garden. Garden. In it is a small garden. Yeah, good. Hadeeqa, ghoot, fadeeqa. Ghoot, fadeeqa. Whoever is reading, let them try to figure it out because that's how, inshaAllah, we will learn.\n\n19\n00:18:00,140 --> 00:18:59,220\n[SPEAKER_00] This is my room. Good. Feeha naafiratun kabheeratun wa marweehatun jameeratun. Marwahatun. That's a new word, I think, right? Or did it come before? I think it came before. No, marwahatun. No, maybe it didn't come. Okay. Marwahatun is a fan. It came before. It did, right? What is naafiratun? Nafiratun, that came before. Yeah. What is it? Somebody... Window. Window? Yeah, window. Okay. Hadhi hurfati is my room. Feeha naafiratun kabheeratun. When it says feeha in the... Why is it feeha instead of fee? So what is it going... Think about what it's going back to. What is it referring to? Fadeeqa? Will a garden have a window? No.\n\n20\n00:19:01,460 --> 00:20:00,119\n[SPEAKER_00] Feeha naafiratun. Naafiratun. Naafiratun is what? A window. Yeah. So look... See the... Okay. The general rule for... It's not always the case, but the default is that the dhameer, the pronoun will go back... It will go back to the closest noun that's to it. Right? So you don't have to think far back or maybe it's going all the way back a few sentences. No. The default is that it's going back to the closest thing that was mentioned. Sometimes it will go back to something else. That's a different scenario. But generally speaking, it's going to go back to the closest thing that was mentioned. So what was the closest thing that was mentioned before? Huh? The house. No. No. The window. The window? No, no, no. The room. Oh, the room. Sorry? The room. Yeah. Room. Ghurfati. Okay. Because we're talking about the window itself. We're saying the window is in something. Feeha naafiratun. Naafiratun. Naafiratun. Naafiratun. Naafiratun. Naafiratun.\n\n21\n00:20:00,119 --> 00:21:00,000\n[SPEAKER_00] In the room is a big window with... Fan. With a beautiful fan. And a beautiful fan, yeah. And a beautiful fan. And. Hatha shariri wa hatha kursi wa hatha maktabi. This is my bed and this is my chair and this is my desk. So basically he's giving a tour of the room. Of his house. Sa'ati wa alami wa kitabi ala al-maktabi. Sa'ati. Sa'ati. This is my clock and my pen and my book and... On the desk. Yeah. Watch would be more likely. Sa'ati could be either watch or clock. So\n\n22\n00:21:00,000 --> 00:21:46,920\n[SPEAKER_00] I don't know. I think over here it's more likely a walk. Allah Allah. Because on a desk. Wa hafibati tahtan maktabi. And my bag is under the desk. Naafiratun. Naafiratun. Naafiratun ghurfati. Naafiratun. Sorry? Nafirahu ghurfati. Sorry? Naafirahu. It's At-ta Marbuta. Naafiratu ghurfati maftuhat. Mafthuhatu. Mapleha? Maftuhat. Tun. Good. Yeah. Okay. My question to you is why is it not Naafiratun. Naafiratun ghurfati.\n\n23\n00:22:00,279 --> 00:23:00,319\n[SPEAKER_00] So remember مضاف cannot get تنوين Okay continue This is Yeah If you were to say this room is my brother's You would say it like this You get the difference? So you're You translated it as This room is my brother's Right But Remember we learned that if you were to say that You would say This room Belongs to my brother But if you wanted to say This is my brother's room You would say it like this This\n\n24\n00:23:00,319 --> 00:24:00,140\n[SPEAKER_00] is my brother's room Yeah That's why it's Yeah Yeah And that is my sister's room My brother's room is big And my sister's room is small I wonder why that's the case My brother's room is in front of the kitchen My brother's room is in front of the kitchen My brother's room is in front of the kitchen Which room? Oh in front of my room And my Why is it If it's a female? What else would it be? So what were you thinking? I was thinking it was like Because her words Yeah but over here they're not using\n\n25\n00:24:00,140 --> 00:24:59,579\n[SPEAKER_00] a pronoun at all It's just Yeah And my sister was like No This is a In front of the bathroom In front of the kitchen Kitchen yeah That's where it's supposed to be My brother My brother My brother My brother My brother My brother My brother I belong So what does For example What does that mean? This book belongs to Simon Okay So now Okay And then what comes after it? Okay\n\n26\n00:25:03,220 --> 00:25:59,819\n[SPEAKER_00] You say I have I have one brother Okay I have one brother His name is Usama And I have one sister Her name is Suad Say it again Fi No It should be Kasra Yeah Because of Fi Translate Yeah It's kind of This is I don't want to confuse you guys With this point But But basically\n\n27\n00:26:00,519 --> 00:27:00,079\n[SPEAKER_00] Just consider In terms of This point About Fi Consider it As if it's not there So it's as if Fi is affecting Al-Ghurfa And Kabira directly Yeah good Yeah it's Yeah Yeah Are in that Big room Good Easy time you're raising your hand Uh Thinker Honorable I I I love Umme Uh Abi Wa umme Wa ah Wa uhibbu Ahi Wa uhdi Wa uhdi Uh Uh Uh Uh Uh Uh Uh Uh Uh Uh Uh Uh Love Love Love It's more for love Right Love Love Love I love my\n\n28\n00:27:00,079 --> 00:28:00,140\n[SPEAKER_00] I love my father And my mother And I love my brother And sister And my sister Okay good Mashallah Alright So what do we learn From this Lesson So We kind of already Did this part Fi He and Fi Ha Right We already Went over that In the last lesson Because We were giving A lot of examples From the past Of Quran and stuff So But they just wanted To highlight Specifically That when you attach The dhamir To Fi It looks like this Fi He And Fi Ha In it Right So Man fi ha The bait Fi He Hamidun Somebody translate this Read and translate Who's in this room Bait Oh sorry In the house In this house Hamid is in it Fi Hamidun Yeah good So also They're trying to emphasize That\n\n29\n00:28:00,140 --> 00:28:59,039\n[SPEAKER_00] Fi He Will Come first Many times Right Well it's not Always the case But many times It will come first So for example You won't normally say Hamidun Fi He You'll say Fi He Hamidun Get it That's generally The case For example In Surah Bayyinah Fi Ha Kutubun Qayyimah Okay But it's not always the case But yeah Continue next Do you want to read number two? Maalikin Akimati Mm-hmm Good What is in the bag? Mm-hmm My books My pen And my notebook Good In it In it is my pen My book My pen and my notebook Very good Mashallah Alright Hafidu Qasha Ha Ha Ha Ha\n\n30\n00:29:09,399 --> 00:30:00,059\n[SPEAKER_00] Who's in the car? In it is my My father My mother My brother And my sister Good Um Brother Ali Next one Manfi Masjid Jamia Jamia Then Um Ali Al-Ana Al-Ana Al-Ana Jamia Jamia Jamia Mm-hmm Uh Uh What is Um Ahad Uh-huh Mm-hmm Uh Who is in the University Who is in the Islamic University What is masjid Masjid You know what masjid means So what is What is this in terms\n\n31\n00:30:00,059 --> 00:31:00,279\n[SPEAKER_00] of the grammar, in terms of the rules that we learned so far? Masjid al-jami'ati. Which one? Yeah, which rule is it? I'm not sure. For example, kitab al-hamidin. What rule is that? Yeah, so same thing. Here. Masjid al-jami'ati. Or here's Masjid al-Kadhafi. Al-jami'a, you remember what it means? No, university. Yeah. The masjid of the university, yeah. I mean, it might be foreign to us because we don't really have masjids in our universities, but in... In Arab countries,\n\n32\n00:31:00,359 --> 00:32:00,160\n[SPEAKER_00] they'll have masjids within the university. Okay, who is in the masjid of the university? Al-an means? I'm not sure. I don't know. No. Yeah, al-an means right now. This is a very common word we should all know. No, that would be... No, in Arabic, that's called... Al-masjid al-jami'u. Al-masjid al-jami'u is a jami'a masjid. Yeah. Al-masjid al-jami'u. There's no time to put on it. And it's... What's the difference between saying masjid al-jami'a at the an and masjid al-jami'a at the an? Like, what's the difference between an and al-an? It's just that you're supposed to say al-jami'a til-ana because hamdat al-wasl. Remember, hamdat al-wasl, you're not supposed to pronounce it if it's in the middle of... No, like, is\n\n33\n00:32:00,160 --> 00:33:00,200\n[SPEAKER_00] there a difference between putting the al in the front? What do you mean? It does have al-an in it. Like, the word is an, right? Al-an. Yeah. Okay, ma-fi-hi ahadun. In it is... Ahadun. So, what does ma mean over here in this context? It's no... So, basically, remember, yeah, we learned there's two possibilities. Whenever you see ma now, you should think, at least for now, for us, because we didn't learn all the other possibilities, like five, six, seven possibilities for ma. But for now, we only learned two possibilities for ma. What are they? Yeah, one is, sorry? What and? Yeah. So, either you're asking a question, ma hadha, what is this? Or you're negating, you're saying, ma andi sayyaratun, I do not have, right? Right? Either you're negating, or either you're asking\n\n34\n00:33:00,200 --> 00:34:00,160\n[SPEAKER_00] a question, right? So, over here, which one is it? What do you think? Negating. Yeah, good. Ahad means a single person, yeah? So, if you're saying ma-fi-hi ahadun, it means nobody, there's nobody in it. Good. Ma-fi-hi ahadun, there's nobody in it. Alright. Last one? Anybody? Man-fi-ha-fi-hi-ruh-h-hadi. Mm-hmm. Fi-ha-l-mud-i-ruh. Al-mud-i-ruh. Fi-ha-l-mud-i-ruh. Yeah. So, fi is, it's, it's, it's, whatever, it's amal, meaning it's, effect is going on to the ha. So, it doesn't affect the mudir. Okay. Who is in the room? Mm-hmm. This room. This room. Who is in this room? Mm-hmm.\n\n35\n00:34:00,680 --> 00:35:00,279\n[SPEAKER_00] In it is the principal. Good. Very good. Mashallah. Who is in this room? In it is the principal. Okay. Girl principal. Sorry? Is that a girl principal? No, girl principal would be al-mudirat-tu. Fi-ha, the reason why it's a female pronoun is it's going back to the ghurfa, the room in the question. The room is a feminine word, so that's why it's fi-ha. Um, sorry, I'm a little confused. Um, is the ha, like, you, you just said the ha in this case is because it's referring to the room. Mm-hmm. But I thought it's, it's ha because there's a, a human being and not the room itself. Like, the previous examples that we did, anytime there's a human being, then ha is used, but anytime there's an object, then he is used. No, it just depends on whether the object, see, remember, because we learned in Arabic, objects can be either ma-, masculine, or feminine, right? So,\n\n36\n00:35:00,279 --> 00:36:00,619\n[SPEAKER_00] um, over here, al-ghurfa is a feminine object because it has the same rabuta. So, therefore, when you're referring to it, you say fi-ha, that's what it is. If you're translating, you'd say in-it. Yeah. Right? So, what's the it? The it is the... Yeah, exactly. You, you say in-it, whether it's fi-hi or fi-ha, you say in-it, but now you just have to look back at that it that it's referring to. Is it a ma-, masculine word or a feminine word? Mm-hmm. And based on that, you put either fi-hi or fi-ha. So, in number four, when it says ma-fi-hi ahad, ahadun, there's no one in it. It's referring to the masjid. Exactly. The masjid is ma-, masculine, so, therefore, you're saying fi-hi. If you were just to ask about the jami'ah, if it was, if he was going to say, man fi al-jami'ati al-aan, then you would say ma-fi-ha ahad, because al-jami'ah is a feminine word, because it has ha. This is great. Ma-fi-ha is a feminine word, Fatih? Yeah. Hadhi. Yeah. Can we say in\n\n37\n00:36:00,619 --> 00:37:00,360\n[SPEAKER_00] it? Yeah. Fi-ha. But can we say also in this direct? In it, in this. Fi-, in this would be fi-hatha. You get it? But for the pronoun, you would say in it. Yeah, it is a pronoun. This is not a pronoun. For the fi-hi, the previous one, ma-fi-hi ahadun, is that referring to the masjid? Yes. Yeah. It is referring to the masjid, masjid al-jami'ah. Remember we mentioned that when you are talking about mudhaf, mudhaf ilayh, in reality, mudhaf itself is the one thing that is being talked about in the sentence, right? For example, the pen of Hamid, qalam of Hamidin. So you are not talking about Hamid here, you are talking about Hamid's pen. Do you get it? So in that case, whatever you are going to describe after, it is referring to the pen of Hamid, not Hamid. Hamid is irrelevant here, generally speaking. Okay, now we learned a word uhibbu,\n\n38\n00:37:00,860 --> 00:37:58,280\n[SPEAKER_00] right? This is actually a present tense verb, so this is the first present tense verb we are going to learn. So far we have only learned what type of verbs? Farah and Mawli, which is past tense verbs, right? We learned dhabah, dhabdah also we learned, dhabdu, I went, right? So we learned basic things and I gave you guys a whole chart, which inshallah we will be starting to utilize more often inshallah. So that was all for past tense. Now this is the first time we are using a present tense verb, but I am not going to confuse you guys yet by giving you the chart and everything. So for now, just remember that if you want to say you love something or someone, you say uhibbu blank, right? So for example, let's read number one. Saqeef. Uhibbu abi wa ummi. I love my father and my mother. Good. Hafidh Mu'min, number two.\n\n39\n00:38:00,280 --> 00:38:59,380\n[SPEAKER_00] Uhibbu akhi wa akhi. Okay. I love my mother and my sister. Okay. I love my classmate. Good. Uhibbu zamili. Which classmate are you talking about? Zamili. Which one, which one specifically? Ali. MashaAllah, very good. Okay. Number four. Anybody? Uhibbu ustadi. Oh, JazakAllah. Okay. Number five. Uhibbu Allah. Yeah. Okay. Now, we are for the first time introduced to a very, very important rule, right? So if you look at it, it says, Uhibbu Allah. Okay. So, why is it becoming a fatha, right? So far, we've only learned things that make other things, kasra. Now we're learning about things that make other things, fatha.\n\n40\n00:39:00,199 --> 00:40:00,119\n[SPEAKER_00] Why is it becoming fatha? It's because this is a verb, right? So normally with a verb, you have a doer, the one who's doing the action, and then you have the object, which is the thing that the action is being done upon, right? So in Arabic language, generally speaking, the object of the verb gets a fatha, right? In Arabic, it's called, Maf'oolun bihi. Maf'oolun bihi. Maf'oolun bihi. Right? The object of the verb. Everybody understand what's meant by object, right? Right? Yes? Da'awullaha. They made dua. They called to Allah. Da'awullaha. That's why Allah is fatha, right? And there's so many examples in the Qur'an, right? Wa nada ashabu aljannati ashaban\n\n41\n00:40:00,119 --> 00:41:00,059\n[SPEAKER_00] nari. Nada means to call out. The people of Jannah called out to the people of the fire. Ashaban nari. It's fatha because they're the object, they're the one who are being called out to. Understood? You ready? How did you know which one to call? So, do you think that we should name a Qur'an or Esto? Can you like do book step and stop and make room for it? Keep it short. Keep it short. No no no. Okay. And what about two words? there's not necessarily an object there's not necessarily an object that you're doing that to. You get it? So it depends on the nature of the verb. And this is something that you pick up based on how the verb is used in\n\n42\n00:41:00,059 --> 00:41:53,219\n[SPEAKER_00] Arabic. When you say isn't the man receiving the sitting? No, he's doing the sitting. So it doesn't count? Yeah. So basically, so this is a general rule. The مفعول به gets a فتحة and the فاعل if it's mentioned, gets a ضم. For example, ذهب صائم إلى البيت. صائم went to the house. So فاعل is the object. Sorry, the doer. That we already kind of already learned, but we didn't go over the actual rule. But that's a general rule. But the doer gets a ضم and the object gets a فتحة. Right? Like I said, let me just write that example down.\n\n43\n00:42:02,199 --> 00:42:59,519\n[SPEAKER_00] And for حفال, this rule will actually help you a lot for تراوير. Every verb. Every type of verb. This is a past tense of أصحاب أصحاب الجنة أصحاب الجنة ونادى أصحاب الجنة This is ضم because it's the doer of نادى. نادى means to call out, right? So the أصحاب الجنة, the people of جنة, they called out. And who's the object? Who's on the receiving end of the calling out? It's أصحاب النادى. Right? So people of جنة called out to the people of the five, so that's why they're أصحاب النادى. Got it? There's a question here.\n\n44\n00:43:00,679 --> 00:44:00,000\n[SPEAKER_00] So the this, like أهبو أبي أمي. These are human beings. They're not objects. That's why you have the ب in there. When you say أهبو أهبو الله أهبو الله I guess you're defining their lives. No, so basically, because normally for names, you don't add a ي at the end. Right? Yeah, for example, like, you don't say, like, a person's name and say, add a ي at the end. You don't say, for example, مدثري. Right? You don't say it like that. You will say, for example, if he's your classmate, you'll say زميلي مدثر. Right? But you won't say the person's name, say my, even in English, you don't normally say, like, my, my صائم, or my, you know, you don't say that. So same thing, you don't say, so if you want to say, my lord, ربي, then that, you can say that about Allah سبحانه وتعالى. So it's not that, it's not that you can't apply ي to\n\n45\n00:44:00,000 --> 00:45:00,960\n[SPEAKER_00] Allah. It's just that the word Allah is his name. Right? Whereas رب is like a title of Allah سبحانه وتعالى. Therefore, that's why you say ربي. You understand? Okay. It's being done by the companions of the Jinnah, right? So they, that's the doer, it gets the ضم, that's why they're صحابه. And then, the object is the people of the fire. And that gets the فتحة. But the نار, the جنة, they have the قصرة, because they're مضافرة. مضافرة, exactly. Maybe an easier example would be الَّذِي جَمَعَ مَالًا جَمَعَ مَالًا السنسورة هُمَزَةً جَمَعَ مَالًا مَالًا So جَمَع means to gather. مَال means wealth. So the doer is mentioned before هُمَزَةً\n\n46\n00:45:00,960 --> 00:46:00,079\n[SPEAKER_00] لُمَزَةً الَّذِي جَمَعَ مَالًا الْهُمَزَةً لُمَزَةً The slandering backbiter. So he gathers wealth. You get it? So the object is the wealth. That's the thing that the verb is being done upon. The gathering is being done to the wealth. So therefore he's going to get a فَتْحَةً جَمَعَ مَالًا Understood? Yeah? Clear? Why does the doer not have a dhamma? So in this case, the doer is a pronoun. That's something that might get a little confused. We'll do it in the second book, it'll come. It's going to come in that chapter. Sometimes the doer is not mentioned, صَلِحًا is not mentioned clearly. Rather, it's basically implied. Right? So جَمَعَ is actually he gathered. So it's not mentioned clearly in the sentence. But sometimes it is mentioned clearly in the sentence. So when it's mentioned clearly in the sentence, then you give it\n\n47\n00:46:00,079 --> 00:47:00,159\n[SPEAKER_00] a dhamma. Otherwise, it's implied. Understood? Yeah, that too. You could say that in a way. Yeah, نَادَ رَبَّهُ Right? Right. Yeah. That's not, إِذْ نَادَهُ رَبُّهُ Yeah. وَنَادَ نُوحٌ رَبَّهُ There's another example of نَادَ. نَادَ again means to call out. Right? نَادَ نُوحٌ رَبَّهُ رَبَّهُ وَنَادَ So somebody translate this for me. Based on what you know. نُوحٌ رَبَّهُ رَبَّهُ And نُوحٌ رَبَّهُ رَبَّهُ called his Lord. Or called to his Lord. Right? So the subject, I'm sorry, the doer is نُوحٌ رَبَّهُ رَبَّهُ He's\n\n48\n00:47:00,159 --> 00:48:00,019\n[SPEAKER_00] the one who's doing the calling. And the calling is being done to his Lord. So that's why it's getting فَتْحَةً رَبَّهُ Get it? Understood? So this, I mean, the purpose of this lesson wasn't to teach this, but since it came up, I'm just telling you guys now so that you get a head start. So it's going to come up, this actual concept will be much more thoroughly discussed later in the book. But we just need to know that when you say أُحِبُّ If you're going to say كِتَابِ or things like that, then you don't have to worry because even though technically it does have a فَتْحَةً on it because it's the object, but because of the يَا it doesn't show. Right? أُحِبُّ كِتَابِ Right? Technically it should be كِتَابَي Right? It should be a فَتْحَةً, but because of the يَا it doesn't show. So it does have a فَتْحَةً, but it's just not showing. So you just pronounce it as كِتَابِ But when it doesn't have إِ for example, then you're going to have to have فَتْحَةً on it. Right? So if you want to say أُحِبُّ, I love any object or person or thing, you make it فَتْحَةً. Right?\n\n49\n00:48:00,920 --> 00:48:59,679\n[SPEAKER_00] If you're not talking about إِ For example, أُحِبُّ المسجد Right? أُحِبُّ الله أُحِبُّ رسول الله صلى الله عليه وسلم In this one, it ended up with the No, this is فَتْحَةً رَبَّهُ رَبَّهُ Oh no, so you don't consider the pronoun as the end of the word. The word رَبْ is the end. Do you get it? The pronoun is separate. Just consider it as the end. Yeah, exactly. Yeah. I had another example with نَادَة I was wondering why the نُوح doesn't get a تَنْوِيْن, but it's actually in the نُوح after it says وَنَادَة نُوح نِبْنَهُ Yeah, good. وَنَادَة نُوحُنْ إِبْنَهُ It's actually إبْنَهُ Yeah, but because of the حَمْزَةُ الْوَصُلِ rule. Remember I told you the كَسْرَةُ rule, right? So, وَنَادَة نُوحُنْ إِبْنَهُ We did that, I think, in class. Yeah, good example.\n\n50\n00:49:00,739 --> 00:49:53,019\n[SPEAKER_00] Alright, so, I mean, you don't have to know this in detail, because it's going to come in detail later, but just know that if you want to say I love something or somebody, you put a فَتْحَةً on it, right? So, let's read the last few. أُحِبُّ اللَّهَ I love Allah. Keep going, anybody? Brother Haqq? أُحِبُّ النَّبِيَّ النَّبِيَّ النَّبِيَّ I love my Prophet. The Prophet, صلى الله عليه وسلم. If you were to say my Prophet, then you would say أُحِبُّ نَبِيِّي or رَسُولِي But, you're just saying the Prophet, النَّبِيَّ صلى الله عليه وسلم. Alright. Last one. أُحِبُّ اللَّغَةَ Yeah.\n\n51\n00:50:00,000 --> 00:51:00,039\n[SPEAKER_00] Translate? Yeah. Because it's موصوف and صفة. Good. I love the Arabic language, so again you're making it فَتْحَةً because it is مَفْعُولٌ بِهِ, it is the object. Have you understood all that? Yes? Alright, good. Wait, I'm confused now. So, if the object is getting a فَتْحَةً, why number four is it أُحِبُّ أُسْتَدِي؟ I mentioned that basically when there's a يَا, when you're saying كِتَابِي there is technically a فَتْحَةً but it's hidden, right? Because of the يَا, you don't pronounce it. Because it would be like, difficult to pronounce. It would be like أُسْتَدَيِّ So, you just say أُسْتَدِي. It's implied, basically. So, basically if you attach a pronoun, it removes like the effect. Sometimes, not always. Like, for example, over here. رَبَّهُ It still shows, the فَتْحَة still shows رَبَّهُ You get it? So, only in the case of يَا, normally, does\n\n52\n00:51:00,039 --> 00:51:58,880\n[SPEAKER_00] it hide the effect of it. Otherwise, other cases it does, even if there's other pronouns, it will show. Alright, we can end here, inshallah. If I want to say I love the teacher of the Prophet ﷺ, would I say it was كِبُون وَحَبُّ أُسْتَادَيِّ مَدْرَصَةٍ Very good, yeah. وَحَبُّ أُسْتَادَيِّ مَدْرَصَةٍ Alright, inshallah, we'll go on to lesson number 12 on Monday, inshallah. Sorry, Wednesday, right? Okay, Monday, inshallah. And just a heads up, we will not have class on Wednesday, because I'm going to be traveling, inshallah. But we'll continue the Monday after that, inshallah. So, we'll have class this Monday, then no class Wednesday, then we have class the Monday after that. If you guys want to do like a group review session or something together, maybe you could do that. Sorry? اللَّهُمَّ اللَّهُ أَكْبَرُ Years ago, I was studying Spanish, and I was studying Spanish.\n\n53\n00:52:00,699 --> 00:52:32,820\n[SPEAKER_00] I learned Spanish. أَشْهَدُ مَنْ دَايِنَا إِلَّا الَّهُ أَشْهَدُ مَنْ دَايِنَا إِلَىٰ إِلَىٰ إِلَىٰ إِلَىٰ إِنَّا لَّهُ I bear witness that there is none worthy of worship except Allah. I bear witness that Muhammad is the Messenger of Allah.\n",
  "source": {},
  "title": "Pronouns and Structures in Surahs: I‘rāb Focus",
  "summary": "The session reviewed Arabic grammar through exploring pronouns (dama'ir) and their usage in Qur’anic verses, emphasizing gender agreement and contextual references. Key examples included ha, ya, and dharf constructions, with practical applications from the Quran.",
  "key_points": [
    "Pronouns (الضمائر) refer back to the nearest noun (masculine or feminine). Example: fi-hi/fi-ha for 'in it'.",
    "Feminine nouns like nafs (النفس) use laha (لها), despite lacking a ta' marbuta.",
    "Dharf (circumstantial words) indicate place/time. Example: ‘alayka (عليك) from ala + ka, meaning 'upon you'.",
    "Maf’ool bihi (object of verb) takes fatha: uhibbu Allaha (أُحِبُ ٱللَّه).",
    "Yā’ endings hide expected fatha: kitabi (كتابي) instead of kitabaya."
  ],
  "questions": [
    "[00:16:32] Q: Why is 'naafiratun' used with 'fee-ha'? — A: Refers to 'my room', feminine, thus 'ha'."
  ],
  "tags": [
    "Arabic",
    "I‘rāb",
    "Nahw",
    "Pronouns",
    "Quranic Grammar",
    "Beginner"
  ]
}